README.rst
setup.py
pyramid_i18n_helper/__init__.py
pyramid_i18n_helper/domain_views.py
pyramid_i18n_helper/po_views.py
pyramid_i18n_helper/pot_views.py
pyramid_i18n_helper/subscribe.py
pyramid_i18n_helper.egg-info/PKG-INFO
pyramid_i18n_helper.egg-info/SOURCES.txt
pyramid_i18n_helper.egg-info/dependency_links.txt
pyramid_i18n_helper.egg-info/not-zip-safe
pyramid_i18n_helper.egg-info/requires.txt
pyramid_i18n_helper.egg-info/top_level.txt
pyramid_i18n_helper/templates/domain.jinja2
pyramid_i18n_helper/templates/i18n_main_template.jinja2
pyramid_i18n_helper/templates/po.jinja2
pyramid_i18n_helper/templates/pot.jinja2