Metadata-Version: 1.1
Name: pyramid-i18n-helper
Version: 0.3.6
Summary: Small tool to help in i18n and l10n
Home-page: https://github.com/sahama/pyramid_i18n_helper
Author: Sayyid Hamid Mahdavi
Author-email: sayyid.hamid.mahdavi@gmail.com
License: UNKNOWN
Keywords: web wsgi bfg pylons pyramid i18n l10n
Platform: UNKNOWN
Classifier: Programming Language :: Python
Classifier: Framework :: Pyramid
Classifier: Topic :: Software Development :: Internationalization
Classifier: Topic :: Software Development :: Localization
Classifier: Topic :: Internet :: WWW/HTTP
Classifier: Topic :: Internet :: WWW/HTTP :: WSGI :: Application
